canvs_toolbox/__init__.py
canvs_toolbox/general.py
canvs_toolbox/main.py
canvs_toolbox/analytics/__init__.py
canvs_toolbox/analytics/tv.py
canvs_toolbox/api/__init__.py
canvs_toolbox/api/social.py
canvs_toolbox/api/tv.py
canvs_toolbox/api/watch.py
canvs_toolbox/test/__init__.py
testingtool_canvsUser-0.0.1.dist-info/LICENSE.txt
testingtool_canvsUser-0.0.1.dist-info/METADATA
testingtool_canvsUser-0.0.1.dist-info/WHEEL
testingtool_canvsUser-0.0.1.dist-info/top_level.txt
testingtool_canvsUser-0.0.1.dist-info/RECORD
