Metadata-Version: 2.1
Name: testingtool-canvsUser
Version: 0.0.1
Summary: A package for custom canvs analytics
Home-page: https://github.com/dbproductionsLTD/canvs_tools
Author: Janet Huang
Author-email: janet.huang@canvs.ai
License: UNKNOWN
Platform: UNKNOWN
Classifier: Programming Language :: Python :: 3
Classifier: License :: OSI Approved :: MIT License
Classifier: Operating System :: OS Independent
Requires-Python: >=3.6
Requires-Dist: scipy (==1.4.1)
Requires-Dist: numpy (==1.18.2)
Requires-Dist: pandas (==1.0.3)
Requires-Dist: python-dateutil (==2.8.1)
Requires-Dist: pytz (==2019.3)
Requires-Dist: six (==1.14.0)
